process/__init__.py
process/_version.py
process/namespace.py
process/py.typed
process/tag/base.py
process/util/__init__.py
process/util/config.py
process/util/log.py
process/util/pkg.py
process/util/time.py
python_process_core-2025.4.8.154550.dist-info/METADATA
python_process_core-2025.4.8.154550.dist-info/WHEEL
python_process_core-2025.4.8.154550.dist-info/top_level.txt
python_process_core-2025.4.8.154550.dist-info/RECORD
